yxwtools/__init__.py
yxwtools/audio_info.py
yxwtools/format_conv.py
yxwtools/resample.py
yxwtools-0.0.5.dist-info/LICENSE
yxwtools-0.0.5.dist-info/METADATA
yxwtools-0.0.5.dist-info/WHEEL
yxwtools-0.0.5.dist-info/top_level.txt
yxwtools-0.0.5.dist-info/RECORD
