Metadata-Version: 2.1
Name: yxwtools
Version: 0.0.5
Summary: A utility toolkit for myself.
Author-email: yun <15515722313@163.com>
License: MIT License
Project-URL: Homepage, https://github.com/yuyun2000
Classifier: Programming Language :: Python :: 3
Classifier: License :: OSI Approved :: MIT License
Classifier: Operating System :: OS Independent
Requires-Python: >=3.6
License-File: LICENSE
Requires-Dist: pydub
